django_better_choices/__init__.py
django_better_choices/py.typed
django_better_choices-3.1.dist-info/WHEEL
django_better_choices-3.1.dist-info/METADATA
django_better_choices-3.1.dist-info/RECORD
