Metadata-Version: 2.4
Name: django-better-choices
Version: 3.1
Summary: Better choices library for Django web framework
Author: Alexander Lokhman
Author-email: Alexander Lokhman <alex.lokhman@gmail.com>
License-Expression: MIT
Classifier: License :: OSI Approved :: MIT License
Classifier: Intended Audience :: Developers
Classifier: Natural Language :: English
Classifier: Operating System :: OS Independent
Classifier: Programming Language :: Python :: 3 :: Only
Classifier: Programming Language :: Python :: 3
Classifier: Programming Language :: Python :: 3.9
Classifier: Programming Language :: Python :: 3.10
Classifier: Programming Language :: Python :: 3.11
Classifier: Programming Language :: Python :: 3.12
Classifier: Programming Language :: Python :: 3.13
Classifier: Programming Language :: Python :: 3.14
Requires-Dist: typing-extensions>=4.15.0 ; python_full_version < '3.11'
Requires-Python: >=3.9
Project-URL: Source, https://github.com/lokhman/django-better-choices
